[{"Season": "2025", "Rank": 1, "Owner": "Herschey6153", "Wins": 12, "Losses": 2, "PF": 2237.96, "PA": 1887.36, "PPG": 159.85, "Max PF": 2420.92, "Best Score": 221.64, "Champion": false}, {"Season": "2025", "Rank": 2, "Owner": "GreyWaedekin27", "Wins": 9, "Losses": 5, "PF": 2145.18, "PA": 2067.92, "PPG": 153.23, "Max PF": 2310.3, "Best Score": 193.34, "Champion": true}, {"Season": "2025", "Rank": 3, "Owner": "gavinw20", "Wins": 8, "Losses": 6, "PF": 2138.22, "PA": 1930.06, "PPG": 152.73, "Max PF": 2274.26, "Best Score": 205.2, "Champion": false}, {"Season": "2025", "Rank": 4, "Owner": "sethfriedman12", "Wins": 8, "Losses": 6, "PF": 2106.14, "PA": 2030.74, "PPG": 150.44, "Max PF": 2202.36, "Best Score": 175.94, "Champion": false}, {"Season": "2025", "Rank": 5, "Owner": "SvenMoney34", "Wins": 7, "Losses": 7, "PF": 2116.52, "PA": 1915.08, "PPG": 151.18, "Max PF": 2382.42, "Best Score": 181.32, "Champion": false}, {"Season": "2025", "Rank": 6, "Owner": "nchernandez19", "Wins": 7, "Losses": 7, "PF": 1993.9, "PA": 1800.82, "PPG": 142.42, "Max PF": 2015.62, "Best Score": 175.18, "Champion": false}, {"Season": "2025", "Rank": 7, "Owner": "GiantHawkTua", "Wins": 7, "Losses": 7, "PF": 1984.98, "PA": 1899.96, "PPG": 141.78, "Max PF": 2154.46, "Best Score": 194.32, "Champion": false}, {"Season": "2025", "Rank": 8, "Owner": "Akracoon", "Wins": 6, "Losses": 8, "PF": 1965.96, "PA": 1883.3, "PPG": 140.43, "Max PF": 2098.52, "Best Score": 174.52, "Champion": false}, {"Season": "2025", "Rank": 9, "Owner": "ekleiner1123", "Wins": 4, "Losses": 10, "PF": 1822.12, "PA": 2086.22, "PPG": 130.15, "Max PF": 2019.08, "Best Score": 180.56, "Champion": false}, {"Season": "2025", "Rank": 10, "Owner": "jsinykin", "Wins": 2, "Losses": 12, "PF": 1112.9, "PA": 2122.42, "PPG": 79.49, "Max PF": 1920.8, "Best Score": 152.4, "Champion": false}, {"Season": "2024", "Rank": 1, "Owner": "Akracoon", "Wins": 12, "Losses": 2, "PF": 2278.8, "PA": 1867.0, "PPG": 162.77, "Max PF": 2455.9, "Best Score": 174.92, "Champion": false}, {"Season": "2024", "Rank": 2, "Owner": "GreyWaedekin27", "Wins": 11, "Losses": 3, "PF": 2096.34, "PA": 1805.08, "PPG": 149.74, "Max PF": 2338.44, "Best Score": 183.54, "Champion": false}, {"Season": "2024", "Rank": 3, "Owner": "gavinw20", "Wins": 10, "Losses": 4, "PF": 2019.64, "PA": 1882.68, "PPG": 144.26, "Max PF": 2127.78, "Best Score": 186.54, "Champion": false}, {"Season": "2024", "Rank": 4, "Owner": "Herschey6153", "Wins": 9, "Losses": 5, "PF": 2280.52, "PA": 1940.56, "PPG": 162.89, "Max PF": 2532.06, "Best Score": 202.96, "Champion": true}, {"Season": "2024", "Rank": 5, "Owner": "GiantHawkTua", "Wins": 7, "Losses": 7, "PF": 2033.46, "PA": 1867.4, "PPG": 145.25, "Max PF": 2047.1, "Best Score": 183.32, "Champion": false}, {"Season": "2024", "Rank": 6, "Owner": "jsinykin", "Wins": 6, "Losses": 8, "PF": 2070.36, "PA": 1948.92, "PPG": 147.88, "Max PF": 2092.08, "Best Score": 196.86, "Champion": false}, {"Season": "2024", "Rank": 7, "Owner": "nchernandez19", "Wins": 6, "Losses": 8, "PF": 1954.78, "PA": 1866.4, "PPG": 139.63, "Max PF": 2033.24, "Best Score": 221.4, "Champion": false}, {"Season": "2024", "Rank": 8, "Owner": "sethfriedman12", "Wins": 5, "Losses": 9, "PF": 1995.18, "PA": 2019.68, "PPG": 142.51, "Max PF": 2182.48, "Best Score": 175.04, "Champion": false}, {"Season": "2024", "Rank": 9, "Owner": "ekleiner1123", "Wins": 3, "Losses": 11, "PF": 1313.26, "PA": 1975.44, "PPG": 93.8, "Max PF": 1773.66, "Best Score": 166.02, "Champion": false}, {"Season": "2024", "Rank": 10, "Owner": "SvenMoney34", "Wins": 1, "Losses": 13, "PF": 1094.52, "PA": 1963.7, "PPG": 78.18, "Max PF": 2006.74, "Best Score": 146.58, "Champion": false}]