{"season": 2026, "weeks": 14, "source": "sleeper", "scores_recorded": false, "note": "Preseason \u2014 schedule pairings available from Sleeper, scores not yet recorded.", "schedule": [{"week": 1, "matchups": [["ekleiner1123", "gavinw20"], ["Herschey6153", "nchernandez19"], ["jsinykin", "Akracoon"], ["SvenMoney34", "GiantHawkTua"], ["sethfriedman12", "GreyWaedekin27"]]}, {"week": 2, "matchups": [["ekleiner1123", "GreyWaedekin27"], ["Herschey6153", "sethfriedman12"], ["jsinykin", "gavinw20"], ["SvenMoney34", "Akracoon"], ["GiantHawkTua", "nchernandez19"]]}, {"week": 3, "matchups": [["ekleiner1123", "Akracoon"], ["Herschey6153", "GreyWaedekin27"], ["jsinykin", "GiantHawkTua"], ["SvenMoney34", "nchernandez19"], ["sethfriedman12", "gavinw20"]]}, {"week": 4, "matchups": [["ekleiner1123", "Herschey6153"], ["jsinykin", "SvenMoney34"], ["Akracoon", "nchernandez19"], ["GiantHawkTua", "sethfriedman12"], ["GreyWaedekin27", "gavinw20"]]}, {"week": 5, "matchups": [["ekleiner1123", "sethfriedman12"], ["Herschey6153", "gavinw20"], ["jsinykin", "nchernandez19"], ["SvenMoney34", "GreyWaedekin27"], ["Akracoon", "GiantHawkTua"]]}, {"week": 6, "matchups": [["ekleiner1123", "GiantHawkTua"], ["Herschey6153", "jsinykin"], ["SvenMoney34", "sethfriedman12"], ["Akracoon", "GreyWaedekin27"], ["nchernandez19", "gavinw20"]]}, {"week": 7, "matchups": [["ekleiner1123", "SvenMoney34"], ["Herschey6153", "Akracoon"], ["jsinykin", "GreyWaedekin27"], ["GiantHawkTua", "gavinw20"], ["nchernandez19", "sethfriedman12"]]}, {"week": 8, "matchups": [["ekleiner1123", "jsinykin"], ["Herschey6153", "GiantHawkTua"], ["SvenMoney34", "gavinw20"], ["Akracoon", "sethfriedman12"], ["nchernandez19", "GreyWaedekin27"]]}, {"week": 9, "matchups": [["ekleiner1123", "nchernandez19"], ["Herschey6153", "SvenMoney34"], ["jsinykin", "sethfriedman12"], ["Akracoon", "gavinw20"], ["GiantHawkTua", "GreyWaedekin27"]]}, {"week": 10, "matchups": [["ekleiner1123", "gavinw20"], ["Herschey6153", "nchernandez19"], ["jsinykin", "Akracoon"], ["SvenMoney34", "GiantHawkTua"], ["sethfriedman12", "GreyWaedekin27"]]}, {"week": 11, "matchups": [["ekleiner1123", "GreyWaedekin27"], ["Herschey6153", "sethfriedman12"], ["jsinykin", "gavinw20"], ["SvenMoney34", "Akracoon"], ["GiantHawkTua", "nchernandez19"]]}, {"week": 12, "matchups": [["ekleiner1123", "Akracoon"], ["Herschey6153", "GreyWaedekin27"], ["jsinykin", "GiantHawkTua"], ["SvenMoney34", "nchernandez19"], ["sethfriedman12", "gavinw20"]]}, {"week": 13, "matchups": [["ekleiner1123", "Herschey6153"], ["jsinykin", "SvenMoney34"], ["Akracoon", "nchernandez19"], ["GiantHawkTua", "sethfriedman12"], ["GreyWaedekin27", "gavinw20"]]}, {"week": 14, "matchups": [["ekleiner1123", "sethfriedman12"], ["Herschey6153", "gavinw20"], ["jsinykin", "nchernandez19"], ["SvenMoney34", "GreyWaedekin27"], ["Akracoon", "GiantHawkTua"]]}]}